dchartjs/__init__.py
dchartjs/basic_chart.py
dchartjs-0.2.dist-info/LICENSE.txt
dchartjs-0.2.dist-info/METADATA
dchartjs-0.2.dist-info/WHEEL
dchartjs-0.2.dist-info/top_level.txt
dchartjs-0.2.dist-info/RECORD
