Metadata-Version: 2.1
Name: dchartjs
Version: 0.2
Summary: Frontend Charts for django
Home-page: https://github.com/KrezyKiller/dchartjs
Author: Shiva Gangula
Author-email: shiva.gangula@outlook.com
License: MIT
Keywords: dchartjs
Platform: UNKNOWN
